LICENSE
MANIFEST.in
README.rst
lightvolume.cpp
lightvolume.h
lightvolume.py
lightvolume_build.py
setup.py
lightvolume.egg-info/PKG-INFO
lightvolume.egg-info/SOURCES.txt
lightvolume.egg-info/dependency_links.txt
lightvolume.egg-info/requires.txt
lightvolume.egg-info/top_level.txt
vendor/visibility/LICENSE
vendor/visibility/README.md
vendor/visibility/tests/catch.hpp
vendor/visibility/visibility/floats.hpp
vendor/visibility/visibility/primitives.hpp
vendor/visibility/visibility/vector2.hpp
vendor/visibility/visibility/visibility.hpp
visibility/LICENSE
visibility/README.md
visibility/tests/catch.hpp
visibility/visibility/floats.hpp
visibility/visibility/primitives.hpp
visibility/visibility/vector2.hpp
visibility/visibility/visibility.hpp